{
  "_id": "vgbdSplhold00000",
  "_key": "!items!vgbdSplhold00000",
  "name": "Hold",
  "type": "spell",
  "img": "icons/svg/lightning.svg",
  "system": {
    "description": "<p>The Target is Paralyzed for the duration if its HD or Level is equal to or lower than your Level. You can spend Mana to increase your Level for the purposes of this casting by 1 per Mana spent to do so.</p><p>If the Target is an Object, it becomes secured and effectively locked if it is a door, chest, or other means of preventing entry. You must pass a Cast Check any time an attempt is made to manipulate the secured Object to maintain the Focus.</p>",
    "damageType": "",
    "damageBase": "d6",
    "maxDice": 0,
    "effect": "<p>The Target is Paralyzed for the duration if its HD or Level is equal to or lower than your Level. You can spend Mana to increase your Level for the purposes of this casting by 1 per Mana spent to do so.</p><p>If the Target is an Object, it becomes secured and effectively locked if it is a door, chest, or other means of preventing entry. You must pass a Cast Check any time an attempt is made to manipulate the secured Object to maintain the Focus.</p>",
    "critEffect": "<p>Duration is 1 minute (no Focus required).</p>",
    "deliveryTypes": {
      "touch": true,
      "remote": true,
      "imbue": true,
      "cube": true,
      "aura": true,
      "cone": true,
      "glyph": true,
      "line": true,
      "sphere": true
    },
    "durationTypes": {
      "instant": true,
      "focus": true,
      "continual": true
    },
    "castingSkill": "",
    "focusing": false,
    "tags": []
  },
  "reviewed": true
}
