{
  "_id": "vgbdSplleech0000",
  "_key": "!items!vgbdSplleech0000",
  "name": "Leech",
  "type": "spell",
  "img": "icons/svg/lightning.svg",
  "system": {
    "description": "<p>The Target is Sickened for the duration. While Sickened this way, any healing that affects it instead heals you. Any subsequent Castings of this Spell that damage the Sickened Target also heals you for the damage dealt.</p>",
    "damageType": "poison",
    "damageBase": "d6",
    "maxDice": 0,
    "effect": "<p>The Target is Sickened for the duration. While Sickened this way, any healing that affects it instead heals you. Any subsequent Castings of this Spell that damage the Sickened Target also heals you for the damage dealt.</p>",
    "critEffect": "",
    "deliveryTypes": {
      "touch": true,
      "remote": true,
      "imbue": true,
      "cube": true,
      "aura": true,
      "cone": true,
      "glyph": true,
      "line": true,
      "sphere": true
    },
    "durationTypes": {
      "instant": true,
      "focus": true,
      "continual": true
    },
    "castingSkill": "",
    "focusing": false,
    "tags": []
  },
  "reviewed": true
}
